dryjq/__init__.py
dryjq/__main__.py
dryjq/commandline.py
dryjq/commons.py
dryjq/convert.py
dryjq/merge.py
dryjq/queries.py
dryjq/streams.py
dryjq-1.9.1.dist-info/LICENSE
dryjq-1.9.1.dist-info/METADATA
dryjq-1.9.1.dist-info/WHEEL
dryjq-1.9.1.dist-info/entry_points.txt
dryjq-1.9.1.dist-info/top_level.txt
dryjq-1.9.1.dist-info/RECORD
