Metadata-Version: 2.1
Name: dryjq
Version: 1.9.1
Summary: Drastically Reduced YAML / JSON Query
Author-email: Rainer Schwarzbach <undisclosed@example.com>
License: MIT License
Project-URL: Homepage, https://gitlab.com/blackstream-x/python-dryjq
Project-URL: Documentation, https://blackstream-x.gitlab.io/python-dryjq
Project-URL: CI, https://gitlab.com/blackstream-x/python-dryjq/-/pipelines
Project-URL: Bug Tracker, https://gitlab.com/blackstream-x/python-dryjq/-/issues
Project-URL: Source Code, https://gitlab.com/blackstream-x/python-dryjq.git
Keywords: json,yaml,query,extract,convert,merge
Classifier: Development Status :: 5 - Production/Stable
Classifier: Environment :: Console
Classifier: Intended Audience :: Developers
Classifier: License :: OSI Approved :: MIT License
Classifier: Operating System :: OS Independent
Classifier: Programming Language :: Python :: 3
Classifier: Programming Language :: Python :: 3.8
Classifier: Programming Language :: Python :: 3.9
Classifier: Programming Language :: Python :: 3.10
Classifier: Programming Language :: Python :: 3.11
Classifier: Programming Language :: Python :: 3.12
Classifier: Programming Language :: Python :: 3 :: Only
Classifier: Topic :: Software Development :: Libraries
Classifier: Topic :: Text Processing :: Filters
Classifier: Topic :: Utilities
Requires-Python: >=3.8
License-File: LICENSE
Requires-Dist: PyYAML >=6.0
Requires-Dist: serializable-trees >=0.5.1
